TreeBuilder/__init__.py
TreeBuilder/builder.py
data2tree-1.0.2.dist-info/METADATA
data2tree-1.0.2.dist-info/WHEEL
data2tree-1.0.2.dist-info/top_level.txt
data2tree-1.0.2.dist-info/RECORD
