Metadata-Version: 2.1
Name: data2tree
Version: 1.0.2
Summary: Python Generate the data tree recursively
Home-page: https://github.com/zerone40
Author: 01
Author-email: zerone40@163.com
License: UNKNOWN
Platform: UNKNOWN
Classifier: Programming Language :: Python :: 3
Classifier: Operating System :: OS Independent
